Workbook

Sheet Audit cost basis — supplied inp
A1: Audit cost basis — supplied inputs
A2: Promise Ledger — Scenario Model · Base
A4: Variable / dimension | B4: Value
A5: Audit input tokens | B5: =2886 -> 2886
A6: Audit output tokens | B6: =929 -> 929
A7: Input price per million tokens | B7: =2.5 -> 2.5
A8: Output price per million tokens | B8: =10 -> 10
A9: Observability allowance per audit | B9: =0.005 -> 0.005
A10: Opening cash | B10: =50000 -> 50000

Sheet Promise Ledger monthly scenario
A1: Promise Ledger monthly scenarios
A2: Promise Ledger — Scenario Model · Base
A4: Variable / dimension | B4: Value | C4: Value > Growth | D4: Value > Downside
A5: Monitored contracts | B5: =200 -> 200 | C5: =1000 -> 1000 | D5: =25 -> 25
A6: Monthly price per contract | B6: =39 -> 39 | C6: =29 -> 29 | D6: =49 -> 49
A7: Audits per contract per month | B7: =8 -> 8 | C7: =10 -> 10 | D7: =6 -> 6
A8: Monthly audits | B8: ='Promise Ledger monthly scenario'!B5*'Promise Ledger monthly scenario'!B7 -> 1600 | C8: ='Promise Ledger monthly scenario'!C5*'Promise Ledger monthly scenario'!C7 -> 10000 | D8: ='Promise Ledger monthly scenario'!D5*'Promise Ledger monthly scenario'!D7 -> 150
A9: Monthly revenue | B9: ='Promise Ledger monthly scenario'!B5*'Promise Ledger monthly scenario'!B6 -> 7800 | C9: ='Promise Ledger monthly scenario'!C5*'Promise Ledger monthly scenario'!C6 -> 29000 | D9: ='Promise Ledger monthly scenario'!D5*'Promise Ledger monthly scenario'!D6 -> 1225
A10: Model API | B10: =ROUND('Promise Ledger monthly scenario'!B8*'Model inputs'!B6,2) -> 26.41 | C10: =ROUND('Promise Ledger monthly scenario'!C8*'Model inputs'!B7,2) -> 165.05 | D10: =ROUND('Promise Ledger monthly scenario'!D8*'Model inputs'!B8,2) -> 2.48
A11: Observability | B11: ='Promise Ledger monthly scenario'!B8*'Audit cost basis — supplied inp'!B9 -> 8 | C11: ='Promise Ledger monthly scenario'!C8*'Model inputs'!B9 -> 50 | D11: ='Promise Ledger monthly scenario'!D8*'Model inputs'!B10 -> 0.75
A12: Infrastructure | B12: =650 -> 650 | C12: =1800 -> 1800 | D12: =250 -> 250
A13: Support/ops COGS | B13: =1200 -> 1200 | C13: =4500 -> 4500 | D13: =250 -> 250
A14: Total COGS | B14: ='Promise Ledger monthly scenario'!B10+'Promise Ledger monthly scenario'!B11+'Promise Ledger monthly scenario'!B12+'Promise Ledger monthly scenario'!B13 -> 1884.41 | C14: ='Promise Ledger monthly scenario'!C10+'Promise Ledger monthly scenario'!C11+'Promise Ledger monthly scenario'!C12+'Promise Ledger monthly scenario'!C13 -> 6515.05 | D14: ='Promise Ledger monthly scenario'!D10+'Promise Ledger monthly scenario'!D11+'Promise Ledger monthly scenario'!D12+'Promise Ledger monthly scenario'!D13 -> 503.23
A15: Gross margin | B15: =('Promise Ledger monthly scenario'!B9-'Promise Ledger monthly scenario'!B14)/'Promise Ledger monthly scenario'!B9 -> 0.75840897 | C15: =('Promise Ledger monthly scenario'!C9-'Promise Ledger monthly scenario'!C14)/'Promise Ledger monthly scenario'!C9 -> 0.7753431 | D15: =('Promise Ledger monthly scenario'!D9-'Promise Ledger monthly scenario'!D14)/'Promise Ledger monthly scenario'!D9 -> 0.5892
A16: Operating expenses | B16: =12000 -> 12000 | C16: =22000 -> 22000 | D16: =5000 -> 5000
A17: Net cash flow | B17: ='Promise Ledger monthly scenario'!B9-'Promise Ledger monthly scenario'!B14-'Promise Ledger monthly scenario'!B16 -> -6084.41 | C17: ='Promise Ledger monthly scenario'!C9-'Promise Ledger monthly scenario'!C14-'Promise Ledger monthly scenario'!C16 -> 484.95 | D17: ='Promise Ledger monthly scenario'!D9-'Promise Ledger monthly scenario'!D14-'Promise Ledger monthly scenario'!D16 -> -4278.23
A18: Runway (months) | B18: =IF(IF(IF(ISERROR('Promise Ledger monthly scenario'!B17<0),'Promise Ledger monthly scenario'!B17<0,IF('Promise Ledger monthly scenario'!B17="","",'Promise Ledger monthly scenario'!B17<0))="",FALSE,IF(ISERROR('Promise Ledger monthly scenario'!B17<0),'Promise Ledger monthly scenario'!B17<0,IF('Promise Ledger monthly scenario'!B17="","",'Promise Ledger monthly scenario'!B17<0))),ROUND('Audit cost basis — supplied inp'!B10/(-'Promise Ledger monthly scenario'!B17),2),"cash-flow positive") -> 8.22 | C18: =IF(IF(IF(ISERROR('Promise Ledger monthly scenario'!C17<0),'Promise Ledger monthly scenario'!C17<0,IF('Promise Ledger monthly scenario'!C17="","",'Promise Ledger monthly scenario'!C17<0))="",FALSE,IF(ISERROR('Promise Ledger monthly scenario'!C17<0),'Promise Ledger monthly scenario'!C17<0,IF('Promise Ledger monthly scenario'!C17="","",'Promise Ledger monthly scenario'!C17<0))),ROUND('Model inputs'!B11/(-'Promise Ledger monthly scenario'!C17),2),"cash-flow positive") -> cash-flow positive | D18: =IF(IF(IF(ISERROR('Promise Ledger monthly scenario'!D17<0),'Promise Ledger monthly scenario'!D17<0,IF('Promise Ledger monthly scenario'!D17="","",'Promise Ledger monthly scenario'!D17<0))="",FALSE,IF(ISERROR('Promise Ledger monthly scenario'!D17<0),'Promise Ledger monthly scenario'!D17<0,IF('Promise Ledger monthly scenario'!D17="","",'Promise Ledger monthly scenario'!D17<0))),ROUND('Model inputs'!B12/(-'Promise Ledger monthly scenario'!D17),2),"cash-flow positive") -> 11.69

Sheet Model inputs
A1: Model inputs
A2: Integration values are aggregated snapshots; raw source records are not included.
A4: Variables
A5: Variable / segment | B5: Value
A6: Model cost per audit · Base | B6: =('Audit cost basis — supplied inp'!B5*'Audit cost basis — supplied inp'!B7+'Audit cost basis — supplied inp'!B6*'Audit cost basis — supplied inp'!B8)/1000000 -> 0.016505
A7: Model cost per audit · Growth | B7: =('Model inputs'!B13*'Model inputs'!B17+'Model inputs'!B15*'Model inputs'!B19)/1000000 -> 0.016505
A8: Model cost per audit · Downside | B8: =('Model inputs'!B14*'Model inputs'!B18+'Model inputs'!B16*'Model inputs'!B20)/1000000 -> 0.016505
A9: Observability allowance per audit · Growth | B9: =0.005 -> 0.005
A10: Observability allowance per audit · Downside | B10: =0.005 -> 0.005
A11: Opening cash · Growth | B11: =50000 -> 50000
A12: Opening cash · Downside | B12: =50000 -> 50000
A13: Audit input tokens · Growth | B13: =2886 -> 2886
A14: Audit input tokens · Downside | B14: =2886 -> 2886
A15: Audit output tokens · Growth | B15: =929 -> 929
A16: Audit output tokens · Downside | B16: =929 -> 929
A17: Input price per million tokens · Growth | B17: =2.5 -> 2.5
A18: Input price per million tokens · Downside | B18: =2.5 -> 2.5
A19: Output price per million tokens · Growth | B19: =10 -> 10
A20: Output price per million tokens · Downside | B20: =10 -> 10
